emunium/__init__.py
emunium/base.py
emunium/browsers.py
emunium/standalone.py
emunium-2.2.0.dist-info/licenses/LICENSE
emunium-2.2.0.dist-info/METADATA
emunium-2.2.0.dist-info/WHEEL
emunium-2.2.0.dist-info/top_level.txt
emunium-2.2.0.dist-info/RECORD
