Metadata-Version: 2.4
Name: emunium
Version: 2.2.0
Summary: A Python module for automating interactions to mimic human behavior in standalone apps or browsers when using Selenium, Pyppeteer, or Playwright.
Home-page: https://github.com/DedInc/emunium
Author: Maehdakvan
Author-email: visitanimation@google.com
Project-URL: Bug Tracker, https://github.com/DedInc/emunium/issues
Classifier: Programming Language :: Python :: 3
Classifier: License :: OSI Approved :: MIT License
Classifier: Operating System :: OS Independent
Requires-Python: >=3.6
License-File: LICENSE
Requires-Dist: HumanCursor
Requires-Dist: keyboard
Requires-Dist: pyautogui
Dynamic: author
Dynamic: author-email
Dynamic: classifier
Dynamic: description
Dynamic: description-content-type
Dynamic: home-page
Dynamic: license-file
Dynamic: project-url
Dynamic: requires-dist
Dynamic: requires-python
Dynamic: summary
